CHANGELOG
LICENSE
MANIFEST.in
README.txt
UPGRADING
setup.cfg
setup.py
adhocracy_Pylons.egg-info/PKG-INFO
adhocracy_Pylons.egg-info/SOURCES.txt
adhocracy_Pylons.egg-info/dependency_links.txt
adhocracy_Pylons.egg-info/entry_points.txt
adhocracy_Pylons.egg-info/not-zip-safe
adhocracy_Pylons.egg-info/requires.txt
adhocracy_Pylons.egg-info/top_level.txt
pylons/__init__.py
pylons/commands.py
pylons/configuration.py
pylons/error.py
pylons/log.py
pylons/middleware.py
pylons/templating.py
pylons/test.py
pylons/testutil.py
pylons/url.py
pylons/util.py
pylons/wsgiapp.py
pylons/controllers/__init__.py
pylons/controllers/core.py
pylons/controllers/jsonrpc.py
pylons/controllers/util.py
pylons/controllers/xmlrpc.py
pylons/decorators/__init__.py
pylons/decorators/cache.py
pylons/decorators/rest.py
pylons/decorators/secure.py
pylons/decorators/util.py
pylons/i18n/__init__.py
pylons/i18n/translation.py
pylons/media/img/bar-bg.png
pylons/media/img/bg.jpg
pylons/media/img/bg.png
pylons/media/img/favicon.ico
pylons/media/img/hatch-yellow.png
pylons/media/img/header.png
pylons/media/img/highlight.png
pylons/media/img/logo.gif
pylons/media/img/main-nav-bg-on.png
pylons/media/img/main-nav-bg.png
pylons/media/img/plus.jpg
pylons/media/img/pylons-logo.gif
pylons/media/img/pylons-powered-02.png
pylons/media/img/tab-brown.png
pylons/media/img/tab-traceback.png
pylons/media/img/tab-white.png
pylons/media/img/tab-yellow-highlight.png
pylons/media/img/tab-yellow.png
pylons/media/img/warning.gif
pylons/media/javascripts/traceback.js
pylons/media/style/black.css
pylons/media/style/itraceback.css
pylons/media/style/orange.css
pylons/templates/__init__.py
pylons/templates/controller.py_tmpl
pylons/templates/restcontroller.py_tmpl
pylons/templates/test_controller.py_tmpl
pylons/templates/test_restcontroller.py_tmpl
pylons/templates/default_project/MANIFEST.in_tmpl
pylons/templates/default_project/README.txt_tmpl
pylons/templates/default_project/development.ini_tmpl
pylons/templates/default_project/ez_setup.py
pylons/templates/default_project/setup.cfg_tmpl
pylons/templates/default_project/setup.py_tmpl
pylons/templates/default_project/test.ini_tmpl
pylons/templates/default_project/+package+/__init__.py_tmpl
pylons/templates/default_project/+package+/websetup.py_tmpl
