Metadata-Version: 1.1
Name: adhocracy-Pylons
Version: 1.0.2dev-20130226
Summary: Pylons Web Framework
Home-page: http://www.pylonshq.com/
Author: Ben Bangert, Philip Jenvey, James Gardner
Author-email: ben@groovie.org, pjenvey@underboss.org
License: BSD
Keywords: web wsgi lightweight framework sqlalchemy formencode mako templates
Platform: UNKNOWN
Classifier: Development Status :: 5 - Production/Stable
Classifier: Intended Audience :: Developers
Classifier: License :: OSI Approved :: BSD License
Classifier: Framework :: Pylons
Classifier: Programming Language :: Python
Classifier: Programming Language :: Python :: 2 :: Only
Classifier: Topic :: Internet :: WWW/HTTP
Classifier: Topic :: Internet :: WWW/HTTP :: Dynamic Content
Classifier: Topic :: Internet :: WWW/HTTP :: WSGI
Classifier: Topic :: Software Development :: Libraries :: Python Modules
